ansys/lumerical/core/__init__.py
ansys/lumerical/core/autodiscovery.py
ansys_lumerical_core-0.2.0.dist-info/licenses/LICENSE
ansys_lumerical_core-0.2.0.dist-info/WHEEL
ansys_lumerical_core-0.2.0.dist-info/METADATA
ansys_lumerical_core-0.2.0.dist-info/RECORD
