Metadata-Version: 2.4
Name: ansys-lumerical-core
Version: 0.2.0
Summary: Python interface to Ansys Lumerical
Keywords: Ansys,Lumerical,photonics,simulation
Author-email: "ANSYS, Inc." <pyansys.core@ansys.com>
Maintainer-email: "ANSYS, Inc." <pyansys.core@ansys.com>
Requires-Python: >=3.10,<4
License-Expression: MIT
Classifier: Development Status :: 4 - Beta
Classifier: Intended Audience :: Science/Research
Classifier: Topic :: Scientific/Engineering :: Information Analysis
Classifier: Operating System :: OS Independent
Classifier: Programming Language :: Python :: 3.10
Classifier: Programming Language :: Python :: 3.11
Classifier: Programming Language :: Python :: 3.12
Classifier: Programming Language :: Python :: 3.13
License-File: LICENSE
Requires-Dist: ansys-api-lumerical
Requires-Dist: numpy>=1.26
Requires-Dist: ansys-sphinx-theme[autoapi]==1.6.4 ; extra == "doc"
Requires-Dist: numpydoc==1.10.0 ; extra == "doc"
Requires-Dist: sphinx==8.2.3 ; extra == "doc"
Requires-Dist: sphinx-copybutton==0.5.2 ; extra == "doc"
Requires-Dist: sphinx_design==0.6.1 ; extra == "doc"
Requires-Dist: nbsphinx==0.9.8 ; extra == "doc"
Requires-Dist: jupytext==1.18.1 ; extra == "doc"
Requires-Dist: ipykernel==7.1.0 ; extra == "doc"
Requires-Dist: matplotlib==3.10.8 ; extra == "examples"
Requires-Dist: pytest==9.0.2 ; extra == "tests"
Requires-Dist: pytest-cov==7.0.0 ; extra == "tests"
Provides-Extra: doc
Provides-Extra: examples
Provides-Extra: tests
